matterlab_serial_device/__init__.py
matterlab_serial_device/serial_device.py
matterlab_serial_device-1.0.4.dist-info/licenses/LICENSE
matterlab_serial_device-1.0.4.dist-info/METADATA
matterlab_serial_device-1.0.4.dist-info/WHEEL
matterlab_serial_device-1.0.4.dist-info/entry_points.txt
matterlab_serial_device-1.0.4.dist-info/top_level.txt
matterlab_serial_device-1.0.4.dist-info/RECORD
